log_reader/__init__.py
log_reader/admin.py
log_reader/apps.py
log_reader/models.py
log_reader/settings.py
log_reader/tests.py
log_reader/utils.py
log_reader/views.py
log_reader/migrations/__init__.py
log_reader/static/log_reader/css/log_reader.css
log_reader/static/log_reader/js/log_reader.js
log_reader/templates/log_reader/admin/change_list.html
django_log_reader-1.1.9.dist-info/LICENSE
django_log_reader-1.1.9.dist-info/METADATA
django_log_reader-1.1.9.dist-info/WHEEL
django_log_reader-1.1.9.dist-info/top_level.txt
django_log_reader-1.1.9.dist-info/RECORD
